{"assets/images/logo.png":["assets/images/logo.png"],"assets/questions/questions0.json":["assets/questions/questions0.json"],"assets/questions/questions1.json":["assets/questions/questions1.json"],"assets/questions/questions2.json":["assets/questions/questions2.json"],"assets/questions/questions3.json":["assets/questions/questions3.json"],"assets/questions/questions4.json":["assets/questions/questions4.json"],"packages/cupertino_icons/assets/CupertinoIcons.ttf":["packages/cupertino_icons/assets/CupertinoIcons.ttf"]}